metabase_api/__init__.py
metabase_api/_helper_methods.py
metabase_api/_helper_methods_async.py
metabase_api/_rest_methods.py
metabase_api/_rest_methods_async.py
metabase_api/copy_methods.py
metabase_api/copy_methods_async.py
metabase_api/create_methods.py
metabase_api/create_methods_async.py
metabase_api/metabase_api.py
metabase_api/metabase_api_async.py
tests/__init__.py
tests/test_metabase_api.py
metabase_api-3.5.2.dist-info/LICENSE
metabase_api-3.5.2.dist-info/METADATA
metabase_api-3.5.2.dist-info/WHEEL
metabase_api-3.5.2.dist-info/top_level.txt
metabase_api-3.5.2.dist-info/RECORD
