Metadata-Version: 2.1
Name: metabase-api
Version: 3.5.2
Summary: A Python Wrapper for Metabase API
Home-page: https://github.com/vvaezian/metabase_api_python
Author: Vahid Vaezian
Author-email: vahid.vaezian@gmail.com
Classifier: Programming Language :: Python :: 3
Classifier: License :: OSI Approved :: MIT License
Classifier: Operating System :: OS Independent
License-File: LICENSE
Requires-Dist: requests
Requires-Dist: httpx
